CHANGES.rst
LICENSE.rst
MANIFEST.in
README.rst
setup.py
src/Products/__init__.py
src/Products.UserField.egg-info/PKG-INFO
src/Products.UserField.egg-info/SOURCES.txt
src/Products.UserField.egg-info/dependency_links.txt
src/Products.UserField.egg-info/namespace_packages.txt
src/Products.UserField.egg-info/not-zip-safe
src/Products.UserField.egg-info/requires.txt
src/Products.UserField.egg-info/top_level.txt
src/Products/UserField/__init__.py
src/Products/UserField/field.py
src/Products/UserField/utils.py