Metadata-Version: 1.1
Name: Products.UserField
Version: 3.0
Summary: Archetypes Field dealing with Plone Users and assign local roles.
Home-page: https://svn.plone.org/svn/archetypes/MoreFieldsAndWidgets/UserField
Author: BlueDynamics Alliance
Author-email: dev@bluedynamics.com
License: BSD
Keywords: zope zope2 plone archetypes filed user
Platform: UNKNOWN
Classifier: Development Status :: 5 - Production/Stable
Classifier: Environment :: Web Environment
Classifier: Framework :: Zope2
Classifier: License :: OSI Approved :: BSD License
Classifier: Operating System :: OS Independent
Classifier: Programming Language :: Python
Classifier: Topic :: Internet :: WWW/HTTP :: Dynamic Content
